siphon/__init__.py
siphon/typed.py
siphon_dsl-0.5.0.dist-info/METADATA
siphon_dsl-0.5.0.dist-info/WHEEL
siphon_dsl-0.5.0.dist-info/RECORD
