Metadata-Version: 2.4
Name: siphon-dsl
Version: 0.5.0
Summary: Minimal DSL for API data extraction
Project-URL: Homepage, https://github.com/alpeshvas/siphon
Project-URL: Repository, https://github.com/alpeshvas/siphon
Author-email: Your Name <you@example.com>
License: MIT
Keywords: api,data,dsl,extraction,jsonpath
Classifier: Development Status :: 4 - Beta
Classifier: Intended Audience :: Developers
Classifier: License :: OSI Approved :: MIT License
Classifier: Programming Language :: Python :: 3
Classifier: Programming Language :: Python :: 3.10
Classifier: Programming Language :: Python :: 3.11
Classifier: Programming Language :: Python :: 3.12
Classifier: Topic :: Software Development :: Libraries :: Python Modules
Requires-Python: >=3.10
Provides-Extra: http
Requires-Dist: requests>=2.28; extra == 'http'
Provides-Extra: typed
Requires-Dist: pydantic>=2.0; extra == 'typed'
